pyhubtel_sms/__init__.py
pyhubtel_sms/__version__.py
pyhubtel_sms/exceptions.py
pyhubtel_sms/message.py
pyhubtel_sms/sms.py
pyhubtel_sms/utils.py
pyhubtel_sms-0.0.1.dist-info/METADATA
pyhubtel_sms-0.0.1.dist-info/RECORD
pyhubtel_sms-0.0.1.dist-info/WHEEL
pyhubtel_sms-0.0.1.dist-info/top_level.txt
