Metadata-Version: 2.1
Name: pyhubtel-sms
Version: 0.0.1
Summary: An easy to use wrapper for Hubtel's SMS APIs.
Home-page: https://github.com/idadzie/pyhubtel-sms
Author: Isaac Dadzie
Author-email: idadzie.dev@gmail.com
License: Apache 2.0
Keywords: hubtel sms development
Platform: UNKNOWN
Classifier: Development Status :: 4 - Beta
Classifier: Intended Audience :: Developers
Classifier: Natural Language :: English
Classifier: License :: OSI Approved :: Apache Software License
Classifier: Programming Language :: Python :: 2.7
Classifier: Programming Language :: Python :: 3
Classifier: Programming Language :: Python :: 3.4
Classifier: Programming Language :: Python :: 3.5
Classifier: Programming Language :: Python :: 3.6
Requires-Python: >=2.6, !=3.0.*, !=3.1.*, !=3.2.*, !=3.3.*
Requires-Dist: requests (>=2.18.4)
Requires-Dist: phonenumberslite (>=8.9.1)
Requires-Dist: python-dateutil (>=2.7.0)
